mostrarprimo/__init__.py
1primo1-1.0.dist-info/LICENSE.txt
1primo1-1.0.dist-info/METADATA
1primo1-1.0.dist-info/WHEEL
1primo1-1.0.dist-info/top_level.txt
1primo1-1.0.dist-info/RECORD
