Metadata-Version: 2.1
Name: 1primo1
Version: 1.0
Summary: Muestra los numeros primos desde 1 hasta n
Home-page: UNKNOWN
Author: Victor Vieira
Author-email: victorvieiraviggiano@gmail.com
License: GPL
Platform: UNKNOWN
Classifier: Development Status :: 4 - Beta
Classifier: Intended Audience :: Developers
Classifier: Topic :: Utilities
Classifier: License :: OSI Approved :: GNU General Public License v3 (GPLv3)
Classifier: Programming Language :: Python :: 3
